{
	"102": {
		"2825": {
			"name": "BANNED_ACCOUNT_IN_INDEPENDENT_SERVICE_TEMPORARILY",
			"message": "Online services cannot be used.\n\nPlease make a note of the error code\nand visit support.nintendo.com.",
			"short_description": "Your PNID is temporarily banned from this service.",
			"long_description": "The account you are trying to use has been temporarily banned from this service for breaking the rules.",
			"short_solution": "Wait for the ban to expire.",
			"long_solution": "Wait for the ban to expire or appeal it on the forum.",
			"support_link": "https://preten.do/102-2825"
		}
	}
}